workon/__init__.py
workon/__main__.py
workon/cli.py
workon/database.py
workon_cli-0.0.5.dist-info/METADATA
workon_cli-0.0.5.dist-info/WHEEL
workon_cli-0.0.5.dist-info/entry_points.txt
workon_cli-0.0.5.dist-info/top_level.txt
workon_cli-0.0.5.dist-info/RECORD
