Metadata-Version: 2.1
Name: workon-cli
Version: 0.0.5
Summary: A simple project manager
Home-page: https://github.com/unlikeghost/workon
Author: unlikeghost
Author-email: unlikeghost@protonmail.com
License: MIT
Platform: UNKNOWN
Classifier: License :: OSI Approved :: MIT License
Classifier: Programming Language :: Python :: 3
Requires-Dist: typer
